domolibrary_extensions/__init__.py
domolibrary_extensions/_modidx.py
domolibrary_extensions/client.py
domolibrary_extensions/onepass.py
domolibrary_extensions/pgp.py
domolibrary_extensions/Atlassian/__init__.py
domolibrary_extensions/Atlassian/auth.py
domolibrary_extensions/asana/__init__.py
domolibrary_extensions/asana/auth.py
domolibrary_extensions/asana/project.py
domolibrary_extensions/asana/task.py
domolibrary_extensions/asana/user.py
domolibrary_extensions/google/GAuth.py
domolibrary_extensions/google/GDoc.py
domolibrary_extensions/google/GDrive.py
domolibrary_extensions/google/GSearch.py
domolibrary_extensions/google/GSheet.py
domolibrary_extensions/google/__init__.py
domolibrary_extensions/google/routes/__init__.py
domolibrary_extensions/google/routes/drive.py
domolibrary_extensions/jira/__init__.py
domolibrary_extensions/jira/auth.py
domolibrary_extensions/jira/classes.py
domolibrary_extensions/jira/routes.py
domolibrary_extensions/utils/Image.py
domolibrary_extensions/utils/__init__.py
domolibrary_extensions/utils/convert.py
domolibrary_extensions/utils/execution.py
domolibrary_extensions/utils/factory.py
domolibrary_extensions/utils/files.py
domolibrary_extensions/utils/utils.py
domolibrary_extensions/utils/web.py
domolibrary_extensions/utils/xkcd_password.py
domolibrary_extensions/vanilla/Vanilla.py
domolibrary_extensions/vanilla/__init__.py
domolibrary_extensions-0.3.dist-info/licenses/LICENSE
domolibrary_extensions-0.3.dist-info/METADATA
domolibrary_extensions-0.3.dist-info/WHEEL
domolibrary_extensions-0.3.dist-info/entry_points.txt
domolibrary_extensions-0.3.dist-info/top_level.txt
domolibrary_extensions-0.3.dist-info/RECORD
