Metadata-Version: 2.4
Name: domolibrary_extensions
Version: 0.3
Summary: integrate google docs with github
Home-page: https://github.com/jaewilson07/domolibrary_extensions
Author: jaewilson07
Author-email: jaewilson07@gmail.com
License: Apache Software License 2.0
Keywords: nbdev jupyter notebook python
Classifier: Development Status :: 4 - Beta
Classifier: Intended Audience :: Developers
Classifier: Natural Language :: English
Classifier: Programming Language :: Python :: 3.9
Classifier: Programming Language :: Python :: 3.10
Classifier: License :: OSI Approved :: Apache Software License
Requires-Python: >=3.9
License-File: LICENSE
Requires-Dist: black
Requires-Dist: black[jupyter]
Requires-Dist: bs4
Requires-Dist: google-auth-oauthlib
Requires-Dist: google-api-python-client
Requires-Dist: onepasswordconnectsdk
Requires-Dist: httpx
Requires-Dist: jupyterlab
Requires-Dist: jupyterlab-quarto
Requires-Dist: markdownify
Requires-Dist: mdutils
Requires-Dist: nbdev
Requires-Dist: pandas
Requires-Dist: pptx2md
Requires-Dist: python-dotenv
Requires-Dist: chardet
Requires-Dist: pillow
Requires-Dist: PGPy
Requires-Dist: matplotlib
Requires-Dist: scipy
Requires-Dist: xkcdpass
Provides-Extra: dev
Dynamic: author
Dynamic: author-email
Dynamic: classifier
Dynamic: description
Dynamic: description-content-type
Dynamic: home-page
Dynamic: keywords
Dynamic: license
Dynamic: license-file
Dynamic: provides-extra
Dynamic: requires-dist
Dynamic: requires-python
Dynamic: summary
